huffpress/__init__.py
huffpress/auxi/__init__.py
huffpress/auxi/basen.py
huffpress/auxi/idict.py
huffpress/auxi/modes.py
huffpress/huff/HuffNode.py
huffpress/huff/__init__.py
huffpress/huff/hfunctions.py
huffpress/huff/htypes.py
huffpress/press/__init__.py
huffpress/press/compress.py
huffpress/press/decompress.py
huffpress/press/decorators.py
huffpress-1.0.54.dist-info/LICENSE
huffpress-1.0.54.dist-info/METADATA
huffpress-1.0.54.dist-info/WHEEL
huffpress-1.0.54.dist-info/top_level.txt
huffpress-1.0.54.dist-info/RECORD
