Metadata-Version: 2.1
Name: huffpress
Version: 1.0.54
Summary: Library containing Huffman algos and bespoke compressor
Home-page: https://github.com/selphaware/huffpress
Author: Usman Ahmad
Author-email: uahmad3013@outlook.com
License: UNKNOWN
Project-URL: Bug Tracker, https://github.com/selphaware/huffpress/issues
Platform: UNKNOWN
Classifier: Programming Language :: Python :: 3
Classifier: License :: OSI Approved :: MIT License
Classifier: Operating System :: OS Independent
Requires-Python: >=3.6
License-File: LICENSE
Requires-Dist: tqdm (==4.62.1)
